fructosa/__init__.py
fructosa/conf.py
fructosa/constants.py
fructosa/daemon.py
fructosa/error_handling.py
fructosa/fructosad.py
fructosa/heartbeat.py
fructosa/lagent.py
fructosa/lmaster.py
fructosa/lmessage.py
fructosa/logs.py
fructosa/maind.py
fructosa/sensors.py
fructosa/version.py
fructosa/grafana/__init__.py
fructosa/grafana/dashboard.py
fructosa/grafana/node.py
fructosa/ui/__init__.py
fructosa/ui/cl.py
tests/__init__.py
tests/common/__init__.py
tests/common/docker.py
tests/common/init.py
tests/common/logs.py
tests/common/program.py
tests/functional/__init__.py
tests/functional/base_start_stop.py
tests/functional/environment.py
tests/functional/graphite.py
tests/functional/test_fructosad_start_stop.py
tests/functional/test_grafana_dashboard.py
tests/functional/test_graphite.py
tests/functional/test_init_script.py
tests/functional/test_lagent.py
tests/functional/test_lmaster.py
tests/functional/test_resilience.py
tests/functional/utils.py
tests/unit/__init__.py
tests/unit/fructosa/__init__.py
tests/unit/fructosa/aio_tools.py
tests/unit/fructosa/test_conf.py
tests/unit/fructosa/test_daemon.py
tests/unit/fructosa/test_error_handling.py
tests/unit/fructosa/test_fructosad.py
tests/unit/fructosa/test_heartbeat.py
tests/unit/fructosa/test_lagent.py
tests/unit/fructosa/test_lmaster.py
tests/unit/fructosa/test_lmessage.py
tests/unit/fructosa/test_logs.py
tests/unit/fructosa/test_maind.py
tests/unit/fructosa/test_sensors.py
tests/unit/fructosa/grafana/__init__.py
tests/unit/fructosa/grafana/test_dashboard.py
tests/unit/fructosa/ui/__init__.py
tests/unit/fructosa/ui/test_cl.py
FrUCToSA-0.3.2.dist-info/COPYING
FrUCToSA-0.3.2.dist-info/METADATA
FrUCToSA-0.3.2.dist-info/WHEEL
FrUCToSA-0.3.2.dist-info/entry_points.txt
FrUCToSA-0.3.2.dist-info/top_level.txt
FrUCToSA-0.3.2.dist-info/RECORD
