Metadata-Version: 2.1
Name: FrUCToSA
Version: 0.3.2
Summary: A package to collect and analyze basic performance data from clusters
Home-page: https://itp.uni-frankfurt.de/~palao/software/FrUCToSA
Author: David Palao
Author-email: palao@csc.uni-frankfurt.de
License: GNU General Public License (GPLv3)
Platform: GNU/Linux
Classifier: Development Status :: 4 - Beta
Classifier: Environment :: Console
Classifier: Environment :: No Input/Output (Daemon)
Classifier: Framework :: AsyncIO
Classifier: Intended Audience :: System Administrators
Classifier: License :: OSI Approved :: GNU General Public License v3 (GPLv3)
Classifier: Natural Language :: English
Classifier: Operating System :: POSIX :: Linux
Classifier: Programming Language :: Python :: 3
Classifier: Programming Language :: Python :: 3.7
Classifier: Programming Language :: Python :: 3.8
Classifier: Programming Language :: Python :: Implementation :: CPython
Classifier: Topic :: System :: Monitoring
Provides: fructosa
Requires-Python: >=3.7
Requires-Dist: psutil
